{
  "LEVELS": [
    {
      "MIN_LEVEL": 0,
      "TRADE_POOL": [
        {
          "value": {
            "OFFER": {
              "item": "the_vault:booster_pack",
              "nbt": "{\"id\": \"the_vault:shiny_pack\"}"
            },
            "CURRENCY": "the_vault:vault_gold",
            "MIN_COST": 15,
            "MAX_COST": 30
          },
          "weight": 20
        },
        {
          "value": {
            "OFFER": {
              "item": "the_vault:booster_pack",
              "nbt": "{\"id\": \"the_vault:mega_evolution_pack\"}"
            },
            "CURRENCY": "the_vault:vault_gold",
            "MIN_COST": 30,
            "MAX_COST": 40
          },
          "weight": 10
        },
        {
          "value": {
            "OFFER": {
              "item": "the_vault:booster_pack",
              "nbt": "{\"id\": \"the_vault:evolution_pack\"}"
            },
            "CURRENCY": "the_vault:vault_gold",
            "MIN_COST": 15,
            "MAX_COST": 30
          },
          "weight": 20
        },
        {
          "value": {
            "OFFER": {
              "item": "the_vault:booster_pack",
              "nbt": "{\"id\": \"the_vault:wild_pack\"}"
            },
            "CURRENCY": "the_vault:vault_gold",
            "MIN_COST": 2,
            "MAX_COST": 4
          },
          "weight": 20
        },
        {
          "value": {
            "OFFER": {
              "item": "the_vault:booster_pack",
              "nbt": "{\"id\": \"the_vault:resource_pack\"}"
            },
            "CURRENCY": "the_vault:vault_gold",
            "MIN_COST": 15,
            "MAX_COST": 30
          },
          "weight": 24
        },
        {
          "value": {
            "OFFER": {
              "item": "the_vault:booster_pack",
              "nbt": "{\"id\": \"the_vault:stat_pack\"}"
            },
            "CURRENCY": "the_vault:vault_gold",
            "MIN_COST": 10,
            "MAX_COST": 20
          },
          "weight": 32
        },
        {
          "value": {
            "OFFER": {
              "item": "the_vault:booster_pack",
              "nbt": "{\"id\": \"the_vault:arcane_pack\"}"
            },
            "CURRENCY": "the_vault:vault_gold",
            "MIN_COST": 10,
            "MAX_COST": 20
          },
          "weight": 32
        },
        {
          "value": {
            "OFFER": {
              "item": "the_vault:booster_pack",
              "nbt": "{\"id\": \"the_vault:black_pack\"}"
            },
            "CURRENCY": "the_vault:vault_gold",
            "MIN_COST": 16,
            "MAX_COST": 32
          },
          "weight": 20
        },
        {
          "value": {
            "OFFER": {
              "item": "the_vault:booster_pack",
              "nbt": "{\"id\": \"the_vault:dungeon_pack\"}"
            },
            "CURRENCY": "the_vault:vault_gold",
            "MIN_COST": 16,
            "MAX_COST": 32
          },
          "weight": 20
        },
        {
          "value": {
            "OFFER": {
              "item": "the_vault:booster_pack",
              "nbt": "{\"id\": \"the_vault:champion_pack\"}"
            },
            "CURRENCY": "the_vault:vault_gold",
            "MIN_COST": 16,
            "MAX_COST": 32
          },
          "weight": 20
        },
        {
          "value": {
            "OFFER": {
              "item": "the_vault:booster_pack",
              "nbt": "{\"id\": \"the_vault:treasure_pack\"}"
            },
            "CURRENCY": "the_vault:vault_gold",
            "MIN_COST": 30,
            "MAX_COST": 40
          },
          "weight": 4
        },
        {
          "value": {
            "OFFER": {
              "item": "the_vault:booster_pack",
              "nbt": "{\"id\": \"the_vault:hellish_pack\"}"
            },
            "CURRENCY": "the_vault:vault_gold",
            "MIN_COST": 25,
            "MAX_COST": 35
          },
          "weight": 8
        },
        {
          "value": {
            "OFFER": {
              "item": "the_vault:booster_pack",
              "nbt": "{\"id\": \"the_vault:merchant_pack\"}"
            },
            "CURRENCY": "the_vault:vault_gold",
            "MIN_COST": 25,
            "MAX_COST": 35
          },
          "weight": 8
        },
        {
          "value": {
            "OFFER": {
              "item": "the_vault:booster_pack",
              "nbt": "{\"id\": \"the_vault:lost_pack\"}"
            },
            "CURRENCY": "the_vault:vault_gold",
            "MIN_COST": 15,
            "MAX_COST": 30
          },
          "weight": 10
        },
        {
          "value": {
            "OFFER": {
              "item": "the_vault:booster_pack",
              "nbt": "{\"id\": \"the_vault:mix_pack\"}"
            },
            "CURRENCY": "the_vault:vault_gold",
            "MIN_COST": 10,
            "MAX_COST": 20
          },
          "weight": 32
        },
        {
          "value": {
            "OFFER": {
              "item": "the_vault:booster_pack",
              "nbt": "{\"id\": \"the_vault:mega_arcane_pack\"}"
            },
            "CURRENCY": "the_vault:vault_gold",
            "MIN_COST": 20,
            "MAX_COST": 40
          },
          "weight": 16
        },
        {
          "value": {
            "OFFER": {
              "item": "the_vault:booster_pack",
              "nbt": "{\"id\": \"the_vault:mega_stat_pack\"}"
            },
            "CURRENCY": "the_vault:vault_gold",
            "MIN_COST": 20,
            "MAX_COST": 40
          },
          "weight": 16
        },
        {
          "value": {
            "OFFER": {
              "item": "the_vault:booster_pack",
              "nbt": "{\"id\": \"the_vault:mega_mix_pack\"}"
            },
            "CURRENCY": "the_vault:vault_gold",
            "MIN_COST": 20,
            "MAX_COST": 40
          },
          "weight": 16
        },
        {
          "value": {
            "OFFER": {
              "item": "the_vault:booster_pack",
              "nbt": "{\"id\": \"the_vault:temporal_pack\"}"
            },
            "CURRENCY": "the_vault:vault_gold",
            "MIN_COST": 40,
            "MAX_COST": 60
          },
          "weight": 16
        },
        {
          "value": {
            "OFFER": {
              "item": "the_vault:booster_pack",
              "nbt": "{\"id\": \"the_vault:mega_temporal_pack\"}"
            },
            "CURRENCY": "the_vault:vault_gold",
            "MIN_COST": 80,
            "MAX_COST": 120
          },
          "weight": 4
        },
        {
          "value": {
            "OFFER": {
              "item": "the_vault:card_deck",
              "nbt": "{id:\"merchant\"}"
            },
            "CURRENCY": "the_vault:vault_gold",
            "MIN_COST": 12,
            "MAX_COST": 24
          },
          "weight": 16
        },
        {
          "value": {
            "OFFER": {
              "item": "the_vault:card_deck",
              "nbt": "{id:\"starter\"}"
            },
            "CURRENCY": "the_vault:vault_gold",
            "MIN_COST": 1,
            "MAX_COST": 2
          },
          "weight": 8
        },
        {
          "value": {
            "OFFER": {
              "item": "the_vault:card_deck",
              "nbt": "{id:\"large\"}"
            },
            "CURRENCY": "the_vault:vault_gold",
            "MIN_COST": 3,
            "MAX_COST": 5
          },
          "weight": 8
        },
        {
          "value": {
            "OFFER": {
              "item": "the_vault:card_deck",
              "nbt": "{id:\"double\"}"
            },
            "CURRENCY": "the_vault:vault_gold",
            "MIN_COST": 3,
            "MAX_COST": 5
          },
          "weight": 8
        },
        {
          "value": {
            "OFFER": {
              "item": "the_vault:card_deck",
              "nbt": "{id:\"expanded\"}"
            },
            "CURRENCY": "the_vault:vault_gold",
            "MIN_COST": 4,
            "MAX_COST": 5
          },
          "weight": 8
        },
        {
          "value": {
            "OFFER": {
              "item": "the_vault:card_deck",
              "nbt": "{id:\"gdungeon\"}"
            },
            "CURRENCY": "the_vault:vault_gold",
            "MIN_COST": 12,
            "MAX_COST": 24
          },
          "weight": 4
        },
        {
          "value": {
            "OFFER": {
              "item": "the_vault:card_deck",
              "nbt": "{id:\"ldungeon\"}"
            },
            "CURRENCY": "the_vault:vault_gold",
            "MIN_COST": 12,
            "MAX_COST": 24
          },
          "weight": 4
        },
        {
          "value": {
            "OFFER": {
              "item": "the_vault:card_deck",
              "nbt": "{id:\"odungeon\"}"
            },
            "CURRENCY": "the_vault:vault_gold",
            "MIN_COST": 12,
            "MAX_COST": 24
          },
          "weight": 4
        },
        {
          "value": {
            "OFFER": {
              "item": "the_vault:card_deck",
              "nbt": "{id:\"black\"}"
            },
            "CURRENCY": "the_vault:vault_gold",
            "MIN_COST": 12,
            "MAX_COST": 24
          },
          "weight": 4
        },
        {
          "value": {
            "OFFER": {
              "item": "the_vault:card_deck",
              "nbt": "{id:\"lost\"}"
            },
            "CURRENCY": "the_vault:vault_gold",
            "MIN_COST": 12,
            "MAX_COST": 24
          },
          "weight": 4
        },
        {
          "value": {
            "OFFER": {
              "item": "the_vault:card_deck",
              "nbt": "{id:\"champion\"}"
            },
            "CURRENCY": "the_vault:vault_gold",
            "MIN_COST": 12,
            "MAX_COST": 24
          },
          "weight": 4
        },
        {
          "value": {
            "OFFER": {
              "item": "the_vault:card_deck",
              "nbt": "{id:\"bishop\"}"
            },
            "CURRENCY": "the_vault:vault_gold",
            "MIN_COST": 12,
            "MAX_COST": 24
          },
          "weight": 4
        },
        {
          "value": {
            "OFFER": {
              "item": "the_vault:card_deck",
              "nbt": "{id:\"belt\"}"
            },
            "CURRENCY": "the_vault:vault_gold",
            "MIN_COST": 12,
            "MAX_COST": 24
          },
          "weight": 4
        },
        {
          "value": {
            "OFFER": {
              "item": "the_vault:card_deck",
              "nbt": "{id:\"extended\"}"
            },
            "CURRENCY": "the_vault:vault_gold",
            "MIN_COST": 1,
            "MAX_COST": 2
          },
          "weight": 4
        },
        {
          "value": {
            "OFFER": {
              "item": "the_vault:card_deck",
              "nbt": "{id:\"scam\"}"
            },
            "CURRENCY": "the_vault:vault_gold",
            "MIN_COST": 1,
            "MAX_COST": 2
          },
          "weight": 4
        },
        {
          "value": {
            "OFFER": {
              "item": "the_vault:card_deck",
              "nbt": "{id:\"runic\"}"
            },
            "CURRENCY": "the_vault:vault_gold",
            "MIN_COST": 16,
            "MAX_COST": 32
          },
          "weight": 4
        },
        {
          "value": {
            "OFFER": {
              "item": "the_vault:card_deck",
              "nbt": "{id:\"treasure\"}"
            },
            "CURRENCY": "the_vault:vault_gold",
            "MIN_COST": 100,
            "MAX_COST": 200
          },
          "weight": 1
        },
        {
          "value": {
            "OFFER": {
              "item": "the_vault:card_deck",
              "nbt": "{id:\"wold\"}"
            },
            "CURRENCY": "the_vault:vault_gold",
            "MIN_COST": 90,
            "MAX_COST": 180
          },
          "weight": 1
        }
      ]
    }
  ]
}