{
  "tile_processors": [
    {
      "type": "leveled",
      "levels": [
        {
          "level": 0,
          "type": "weighted_target",
          "target": "the_vault:treasure_container",
          "output": {
            "the_vault:treasure_container{Generated:0b,LootTable:\"the_vault:treasure_chest_lvl50\"}": 1
          }
        }
      ]
    },
    {
      "type": "leveled",
      "levels": [
        {
          "level": 0,
          "type": "weighted_target",
          "target": "the_vault:treasure_chest",
          "output": {
            "the_vault:treasure_container{Generated:0b,LootTable:\"the_vault:treasure_chest_lvl50\"}": 1
          }
        }
      ]
    },
    {
        "type": "leveled",
        "levels": [
            {
                "level": 0,
                "type": "weighted_target",
                "target": "the_vault:treasure_pedestal",
                "output": {
                    "the_vault:treasure_pedestal{LootTable:\"the_vault:treasure_pillar\"}": 7,
                    "minecraft:air": 3
                }
            }
        ]
    },
    {
        "type": "leveled",
        "levels": [
            {
                "level": 0,
                "type": "weighted_target",
                "target": "minecraft:light_blue_wool",
                "output": {
                    "the_vault:treasure_pedestal{LootTable:\"the_vault:treasure_pillar\"}": 3,
                    "minecraft:air": 7
                }
            }
        ]
    },
    {
        "type": "leveled",
        "levels": [
            {
                "level": 0,
                "type": "weighted_target",
                "target": "minecraft:blue_wool",
                "output": {
                    "the_vault:treasure_pedestal{LootTable:\"the_vault:treasure_pillar\"}": 1
                }
            }
        ]
    },
    {
      "type": "weighted_target",
      "target": "the_vault:treasure_sand",
      "output": {
        "the_vault:treasure_sand{LootTable:\"the_vault:treasure_sand_lvl0\"}": 1
      }
    },
    {
      "type": "placeholder",
      "target": "ORE",
      "levels": [
        {
          "level": 0,
          "probability": 0.3,
          "success": {
            "the_vault:ore_painite[type=vault_stone,generated=true]": 75,
            "the_vault:ore_alexandrite[type=vault_stone,generated=true]": 35,
            "the_vault:ore_wutodie[type=vault_stone,generated=true]": 35,
            "the_vault:ore_benitoite[type=vault_stone,generated=true]": 50,
            "the_vault:ore_larimar[type=vault_stone,generated=true]": 40,
            "the_vault:ore_black_opal[type=vault_stone,generated=true]": 75,
            "the_vault:ore_echo[type=vault_stone,generated=true]": 5
          },
          "failure": {
            "the_vault:vault_stone": 1
          }
        }
      ]
    }
  ]
}